{
  "managedSettings": {
    "totalNonStaleRecentDevices": 308,
    "totalRecent24hDevices": 36,
    "totalLicensedDevices": 0,
    "devicesByOS": {
      "26": 1,
      "27": 4,
      "28": 4,
      "29": 15,
      "30": 25,
      "31": 33,
      "32": 5,
      "33": 59,
      "34": 144,
      "35": 18
    },
    "devicesByMake": {
      "samsung": 150,
      "Google": 36,
      "Rhino Mobility": 33,
      "OnePlus": 12,
      "motorola": 11,
      "Xiaomi": 10,
      "RHINO": 8,
      "Zebra Technologies": 7,
      "realme": 5,
      "TCL": 5,
      "vivo": 3,
      "OPPO": 3,
      "Topicon": 3,
      "TECNO MOBILE LIMITED": 2,
      "HONOR": 2,
      "Lenovo": 2,
      "LGE": 2,
      "Crosscall": 2,
      "TECNO": 2,
      "HUAWEI": 2,
      "Honeywell": 1,
      "Nothing": 1,
      "iWaylink": 1,
      "ITEL": 1,
      "Amazon": 1,
      "Hisense": 1,
      "Sky_Devices": 1,
      "Microsoft": 1
    },
    "numberChangeByOS": {
      "26": 0,
      "27": 0,
      "28": 0,
      "29": 1,
      "30": 0,
      "31": 0,
      "32": 0,
      "33": -2,
      "34": -1,
      "35": 0
    },
    "numberChangeByMake": {
      "samsung": 0,
      "Google": -1,
      "Rhino Mobility": -1,
      "OnePlus": 0,
      "motorola": 0,
      "Xiaomi": 1,
      "RHINO": 0,
      "Zebra Technologies": 0,
      "realme": 0,
      "TCL": 0,
      "vivo": 0,
      "OPPO": 0,
      "Topicon": 0,
      "TECNO MOBILE LIMITED": 0,
      "HONOR": 0,
      "Lenovo": 0,
      "LGE": 0,
      "Crosscall": 0,
      "TECNO": -1,
      "HUAWEI": 0,
      "Honeywell": 0,
      "Nothing": 0,
      "iWaylink": 0,
      "ITEL": 0,
      "Amazon": 0,
      "Hisense": 0,
      "Sky_Devices": 0,
      "Microsoft": 0
    }
  },
  "packageSearch": {
    "totalNonStaleRecentDevices": 418,
    "totalRecent24hDevices": 27,
    "totalLicensedDevices": 0,
    "devicesByOS": {
      "26": 1,
      "27": 13,
      "28": 9,
      "29": 4,
      "30": 91,
      "31": 22,
      "32": 25,
      "33": 37,
      "34": 151,
      "35": 65
    },
    "devicesByMake": {
      "Google": 191,
      "samsung": 84,
      "motorola": 45,
      "OnePlus": 41,
      "Nothing": 7,
      "HONOR": 7,
      "LGE": 6,
      "MobiWire": 6,
      "unknown": 5,
      "RHINO": 4,
      "LENOVO": 4,
      "Zebra Technologies": 2,
      "realme": 2,
      "vivo": 1,
      "OPPO": 1,
      "HMD Global": 1,
      "Acer": 1,
      "Rhino Mobility": 1,
      "TECNO MOBILE LIMITED": 1,
      "Sony": 1,
      "Honeywell": 1,
      "QEMU": 1,
      "TCL": 1,
      "Weiheng digital company limited": 1,
      "Xiaomi": 1,
      "Microsoft": 1,
      "Fairphone": 1
    },
    "numberChangeByOS": {
      "26": 0,
      "27": -1,
      "28": 0,
      "29": 0,
      "30": -5,
      "31": -1,
      "32": -1,
      "33": -2,
      "34": -4,
      "35": 0
    },
    "numberChangeByMake": {
      "Google": -5,
      "samsung": -3,
      "motorola": -4,
      "OnePlus": -2,
      "Nothing": 0,
      "HONOR": 0,
      "LGE": 0,
      "MobiWire": 0,
      "unknown": 0,
      "RHINO": 0,
      "LENOVO": 0,
      "Zebra Technologies": 0,
      "realme": 0,
      "vivo": 0,
      "OPPO": 0,
      "HMD Global": 0,
      "Acer": 0,
      "Rhino Mobility": 0,
      "TECNO MOBILE LIMITED": 0,
      "Sony": 0,
      "Honeywell": 0,
      "QEMU": 0,
      "TCL": 0,
      "Weiheng digital company limited": 0,
      "Xiaomi": 0,
      "Microsoft": 0,
      "Fairphone": 0
    }
  },
  "managedInfo": {
    "totalNonStaleRecentDevices": 136,
    "totalRecent24hDevices": 5,
    "totalLicensedDevices": 46,
    "devicesByOS": {
      "28": 3,
      "30": 40,
      "31": 10,
      "32": 5,
      "33": 2,
      "34": 32,
      "35": 44
    },
    "devicesByMake": {
      "Google": 73,
      "OnePlus": 39,
      "samsung": 9,
      "HONOR": 6,
      "unknown": 3,
      "RHINO": 2,
      "Rhino Mobility": 1,
      "Xiaomi": 1,
      "motorola": 1,
      "LENOVO": 1
    },
    "numberChangeByOS": {
      "28": 0,
      "30": 0,
      "31": 0,
      "32": 0,
      "33": 0,
      "34": 1,
      "35": 0
    },
    "numberChangeByMake": {
      "Google": 0,
      "OnePlus": 0,
      "samsung": 1,
      "HONOR": 0,
      "unknown": 0,
      "RHINO": 0,
      "Rhino Mobility": 0,
      "Xiaomi": 0,
      "motorola": 0,
      "LENOVO": 0
    }
  }
}