{
  "managedSettings": {
    "totalNonStaleRecentDevices": 6159,
    "totalRecent24hDevices": 1450,
    "totalLicensedDevices": 0,
    "devicesByOS": {
      "24": 10,
      "25": 8,
      "26": 11,
      "27": 68,
      "28": 52,
      "29": 223,
      "30": 380,
      "31": 418,
      "32": 45,
      "33": 455,
      "34": 1354,
      "35": 2702,
      "36": 433
    },
    "devicesByMake": {
      "motorola": 2295,
      "samsung": 1577,
      "Ulefone": 454,
      "Zebra Technologies": 343,
      "Xiaomi": 202,
      "HONOR": 201,
      "OPPO": 131,
      "vivo": 113,
      "realme": 109,
      "Elo Touch Solutions": 70,
      "LENOVO": 69,
      "codex": 63,
      "Honeywell": 53,
      "INFINIX": 49,
      "HMD Global": 38,
      "TECNO": 37,
      "OnePlus": 32,
      "ITEL": 25,
      "Blackview": 23,
      "HUAWEI": 22,
      "TECNO MOBILE LIMITED": 21,
      "Gigaset": 17,
      "INFINIX MOBILITY LIMITED": 16,
      "incar": 13,
      "Google": 13,
      "COLORROOM": 12,
      "Freeski": 11,
      "TCL": 10,
      "LGE": 9,
      "LAVA": 9,
      "itel": 7,
      "DOOGEE": 7,
      "iMin Technology": 7,
      "ZTE": 6,
      "Datalogic": 6,
      "ITEL MOBILE LIMITED": 4,
      "Symphony": 3,
      "JUEDUR": 3,
      "WALTON": 3,
      "Realme": 3,
      "Mobicel": 3,
      "FUJITSU": 3,
      "reeder": 3,
      "LT": 2,
      "amlogic": 2,
      "Oculus": 2,
      "Rhino Mobility": 2,
      "OUKITEL": 2,
      "ACE France": 2,
      "Crosscall": 2,
      "JIMI": 2,
      "Topicon": 1,
      "Generic": 1,
      "QEMU": 1,
      "Lava": 1,
      "Premier Code (PRIVATE) LIMITED": 1,
      "Ascom": 1,
      "SSH Telecom SMC (Pvt.) Ltd": 1,
      "alps": 1,
      "FIH": 1,
      "KYOCERA": 1,
      "MediaTek": 1,
      "Nothing": 1,
      "H19": 1,
      "Welcome": 1,
      "unnecto": 1,
      "Micromax": 1,
      "ASR": 1,
      "rockchip": 1,
      "Dcode Cygnal 3 Lite": 1,
      "Maxwest": 1,
      "Chinoe": 1,
      "BLU": 1,
      "INOI Limited": 1,
      "Sony": 1,
      "nubia": 1,
      "DW100Ultra": 1,
      "FCNT": 1,
      "Hisense": 1,
      "OTEETO": 1,
      "TINNO": 1,
      "M-KOPA": 1,
      "CUBOT": 1,
      "Safaricom": 1,
      "Hivendor": 1,
      "VILLAON": 1,
      "Fairphone": 1,
      "wheatek": 1,
      "LT_mobile": 1,
      "Vortex": 1,
      "SHARP": 1,
      "Cloud Mobile": 1,
      "A73": 1,
      "RockChip": 1,
      "Calme": 1,
      "Infinix": 1,
      "Multilaser": 1,
      "Janam Technologies": 1,
      "INOI": 1
    },
    "devicesByCountry": {
      "BR": 2561,
      "US": 626,
      "DE": 552,
      "ZA": 433,
      "IN": 390,
      "EG": 205,
      "GB": 163,
      "SE": 145,
      "MX": 75,
      "IT": 70,
      "BD": 54,
      "PK": 53,
      "IL": 51,
      "PH": 45,
      "ES": 44,
      "FI": 39,
      "NO": 32,
      "PL": 32,
      "SA": 31,
      "AT": 29,
      "YE": 27,
      "NL": 26,
      "MM": 24,
      "DZ": 23,
      "DK": 23,
      "ID": 22,
      "ET": 17,
      "TH": 15,
      "NP": 14,
      "CZ": 13,
      "RU": 12,
      "CH": 12,
      "SK": 11,
      "MY": 10,
      "TR": 10,
      "SD": 10,
      "MA": 10,
      "UZ": 8,
      "IQ": 7,
      "KE": 7,
      "LV": 6,
      "IR": 6,
      "EE": 6,
      "FR": 6,
      "BW": 6,
      "LK": 6,
      "VN": 5,
      "BE": 5,
      "BI": 5,
      "SN": 5,
      "AU": 5,
      "PE": 5,
      "GH": 5,
      "LT": 5,
      "UA": 4,
      "NG": 4,
      "CA": 4,
      "GR": 4,
      "JO": 4,
      "AF": 4,
      "TZ": 4,
      "SG": 4,
      "RO": 4,
      "ZM": 3,
      "BG": 3,
      "ZW": 3,
      "CO": 3,
      "AR": 3,
      "LA": 3,
      "TJ": 3,
      "LY": 3,
      "KW": 3,
      "JP": 3,
      "KZ": 3,
      "TM": 3,
      "BO": 2,
      "SO": 2,
      "NA": 2,
      "BF": 2,
      "OM": 2,
      "AZ": 2,
      "CN": 2,
      "LS": 2,
      "VE": 2,
      "PT": 2,
      "NZ": 2,
      "MW": 2,
      "IE": 2,
      "EC": 2,
      "TD": 2,
      "GT": 2,
      "MD": 2,
      "UG": 2,
      "NI": 2,
      "DO": 2,
      "AE": 2,
      "LB": 2,
      "AM": 2,
      "PA": 2,
      "HN": 2,
      "AL": 1,
      "TT": 1,
      "BH": 1,
      "HU": 1,
      "MG": 1,
      "KH": 1,
      "KM": 1,
      "CI": 1,
      "PG": 1,
      "TW": 1,
      "SI": 1,
      "CU": 1,
      "ML": 1,
      "SV": 1,
      "GY": 1,
      "VC": 1,
      "JM": 1,
      "CM": 1,
      "TN": 1,
      "PY": 1,
      "CL": 1,
      "KR": 1,
      "SY": 1,
      "GN": 1,
      "MZ": 1,
      "CG": 1,
      "WS": 1,
      "MN": 1,
      "RS": 1,
      "GE": 1
    },
    "numberChangeByOS": {
      "24": 0,
      "25": 0,
      "26": 0,
      "27": 1,
      "28": 1,
      "29": 3,
      "30": -1,
      "31": 4,
      "32": 1,
      "33": 3,
      "34": -2,
      "35": 24,
      "36": 4
    },
    "numberChangeByMake": {
      "motorola": 7,
      "samsung": 7,
      "Ulefone": 12,
      "Zebra Technologies": 3,
      "Xiaomi": 2,
      "HONOR": 0,
      "OPPO": 0,
      "vivo": 1,
      "realme": -2,
      "Elo Touch Solutions": 0,
      "LENOVO": 1,
      "codex": 0,
      "Honeywell": 1,
      "INFINIX": 1,
      "HMD Global": 0,
      "TECNO": 1,
      "OnePlus": 1,
      "ITEL": 0,
      "Blackview": 0,
      "HUAWEI": 0,
      "TECNO MOBILE LIMITED": 0,
      "Gigaset": 0,
      "INFINIX MOBILITY LIMITED": 0,
      "incar": -1,
      "Google": 0,
      "COLORROOM": 0,
      "Freeski": 0,
      "TCL": 0,
      "LGE": 1,
      "LAVA": 0,
      "itel": 0,
      "DOOGEE": 2,
      "iMin Technology": 0,
      "ZTE": -1,
      "Datalogic": 0,
      "ITEL MOBILE LIMITED": 0,
      "Symphony": 0,
      "JUEDUR": 0,
      "WALTON": 0,
      "Realme": 0,
      "Mobicel": 0,
      "FUJITSU": 0,
      "reeder": 0,
      "LT": 0,
      "amlogic": 0,
      "Oculus": 0,
      "Rhino Mobility": 0,
      "OUKITEL": 0,
      "ACE France": 0,
      "Crosscall": 0,
      "JIMI": 0,
      "Topicon": 0,
      "Generic": 0,
      "QEMU": 0,
      "Lava": 0,
      "Premier Code (PRIVATE) LIMITED": 1,
      "Ascom": 0,
      "SSH Telecom SMC (Pvt.) Ltd": 0,
      "alps": 0,
      "FIH": 0,
      "KYOCERA": 0,
      "MediaTek": 0,
      "Nothing": 0,
      "H19": 0,
      "Welcome": 0,
      "unnecto": 0,
      "Micromax": 0,
      "ASR": 0,
      "rockchip": 0,
      "Dcode Cygnal 3 Lite": 0,
      "Maxwest": 0,
      "Chinoe": 0,
      "BLU": 0,
      "INOI Limited": 0,
      "Sony": 0,
      "nubia": 0,
      "DW100Ultra": 0,
      "FCNT": 0,
      "Hisense": 0,
      "OTEETO": 0,
      "TINNO": 0,
      "M-KOPA": 0,
      "CUBOT": 0,
      "Safaricom": 0,
      "Hivendor": 0,
      "VILLAON": 0,
      "Fairphone": 0,
      "wheatek": 0,
      "LT_mobile": 0,
      "Vortex": 0,
      "SHARP": 0,
      "Cloud Mobile": 0,
      "A73": 0,
      "RockChip": 1,
      "Calme": 0,
      "Infinix": 0,
      "Multilaser": 0,
      "Janam Technologies": 0,
      "INOI": 0
    },
    "numberChangeByCountry": {
      "BR": 8,
      "US": 3,
      "DE": 11,
      "ZA": 12,
      "IN": 3,
      "EG": 0,
      "GB": -2,
      "SE": 2,
      "MX": 1,
      "IT": 1,
      "BD": 1,
      "PK": 1,
      "IL": 0,
      "PH": 0,
      "ES": 1,
      "FI": 0,
      "NO": 0,
      "PL": 0,
      "SA": -1,
      "AT": 0,
      "YE": 1,
      "NL": -1,
      "MM": 0,
      "DZ": 0,
      "DK": -2,
      "ID": 0,
      "ET": 0,
      "TH": 0,
      "NP": 0,
      "CZ": 0,
      "RU": 0,
      "CH": 0,
      "SK": 0,
      "MY": -1,
      "TR": 0,
      "SD": 0,
      "MA": 0,
      "UZ": 0,
      "IQ": 0,
      "KE": 0,
      "LV": 0,
      "IR": 0,
      "EE": 0,
      "FR": -2,
      "BW": 0,
      "LK": 0,
      "VN": 0,
      "BE": 2,
      "BI": 0,
      "SN": 0,
      "AU": 0,
      "PE": 0,
      "GH": 0,
      "LT": 0,
      "UA": 0,
      "NG": 0,
      "CA": 0,
      "GR": 0,
      "JO": 0,
      "AF": 0,
      "TZ": -1,
      "SG": 0,
      "RO": 0,
      "ZM": 0,
      "BG": 0,
      "ZW": 0,
      "CO": 0,
      "AR": 0,
      "LA": 0,
      "TJ": 0,
      "LY": 0,
      "KW": 0,
      "JP": 0,
      "KZ": 0,
      "TM": 0,
      "BO": 0,
      "SO": 0,
      "NA": 0,
      "BF": 0,
      "OM": 0,
      "AZ": 0,
      "CN": 0,
      "LS": 0,
      "VE": 1,
      "PT": 0,
      "NZ": 0,
      "MW": 0,
      "IE": 0,
      "EC": 0,
      "TD": 0,
      "GT": 0,
      "MD": 0,
      "UG": 0,
      "NI": 0,
      "DO": 0,
      "AE": 0,
      "LB": 0,
      "AM": 0,
      "PA": 0,
      "HN": 0,
      "AL": 0,
      "TT": 0,
      "BH": 0,
      "HU": 0,
      "MG": 0,
      "KH": 0,
      "KM": 0,
      "CI": 0,
      "PG": 0,
      "TW": 0,
      "SI": 0,
      "CU": 0,
      "ML": 0,
      "SV": 0,
      "GY": 0,
      "VC": 0,
      "JM": 0,
      "CM": 0,
      "TN": 0,
      "PY": 0,
      "CL": 0,
      "KR": 0,
      "SY": 0,
      "GN": 0,
      "MZ": 0,
      "CG": 0,
      "WS": 0,
      "MN": 0,
      "RS": 0,
      "GE": 0
    }
  },
  "packageSearch": {
    "totalNonStaleRecentDevices": 349,
    "totalRecent24hDevices": 49,
    "totalLicensedDevices": 0,
    "devicesByOS": {
      "25": 4,
      "27": 8,
      "28": 5,
      "29": 3,
      "30": 33,
      "31": 23,
      "32": 3,
      "33": 28,
      "34": 48,
      "35": 71,
      "36": 123
    },
    "devicesByMake": {
      "samsung": 135,
      "Google": 48,
      "motorola": 22,
      "Zebra Technologies": 18,
      "Xiaomi": 15,
      "Fairphone": 13,
      "OnePlus": 12,
      "TCL": 12,
      "Elo Touch Solutions": 10,
      "Lenovo": 8,
      "QEMU": 7,
      "OUKITEL": 6,
      "CHAINWAY": 4,
      "LENOVO": 4,
      "Crosscall": 3,
      "LGE": 3,
      "NUU": 3,
      "CipherLab": 3,
      "OPPO": 3,
      "HONOR": 2,
      "HMD Global": 2,
      "Datalogic": 2,
      "Unihertz": 2,
      "HUAWEI": 1,
      "unknown": 1,
      "Wingtech": 1,
      "Ulefone": 1,
      "SMT_HK": 1,
      "ITEL MOBILE LIMITED": 1,
      "INFINIX": 1,
      "Honeywell": 1,
      "realme": 1,
      "SAMSUNG": 1,
      "CUBOT": 1,
      "Nothing": 1
    },
    "devicesByCountry": {
      "GB": 82,
      "US": 59,
      "DE": 37,
      "FR": 29,
      "ES": 23,
      "AT": 12,
      "SE": 12,
      "IT": 11,
      "CN": 11,
      "NL": 11,
      "AU": 8,
      "PL": 6,
      "NZ": 4,
      "RU": 4,
      "ID": 3,
      "BD": 3,
      "FI": 3,
      "CA": 3,
      "MX": 3,
      "RO": 2,
      "IE": 2,
      "TR": 2,
      "BR": 2,
      "CH": 2,
      "VN": 1,
      "DZ": 1,
      "TT": 1,
      "TW": 1,
      "BE": 1,
      "NO": 1,
      "KE": 1,
      "PK": 1,
      "IN": 1,
      "DK": 1,
      "SO": 1,
      "PH": 1,
      "EG": 1,
      "TH": 1,
      "JP": 1
    },
    "numberChangeByOS": {
      "25": -1,
      "27": 0,
      "28": 0,
      "29": 0,
      "30": 0,
      "31": 0,
      "32": 0,
      "33": 0,
      "34": 1,
      "35": 0,
      "36": -6
    },
    "numberChangeByMake": {
      "samsung": -6,
      "Google": -1,
      "motorola": 0,
      "Zebra Technologies": 0,
      "Xiaomi": 0,
      "Fairphone": 0,
      "OnePlus": 0,
      "TCL": 0,
      "Elo Touch Solutions": 0,
      "Lenovo": 0,
      "QEMU": 0,
      "OUKITEL": 0,
      "CHAINWAY": 0,
      "LENOVO": 0,
      "Crosscall": 0,
      "LGE": 0,
      "NUU": 0,
      "CipherLab": 0,
      "OPPO": 1,
      "HONOR": 0,
      "HMD Global": 0,
      "Datalogic": 0,
      "Unihertz": 0,
      "HUAWEI": 0,
      "unknown": 0,
      "Wingtech": 0,
      "Ulefone": 0,
      "SMT_HK": 0,
      "ITEL MOBILE LIMITED": 0,
      "INFINIX": 0,
      "Honeywell": 0,
      "realme": 0,
      "SAMSUNG": 0,
      "CUBOT": 0,
      "Nothing": 0
    },
    "numberChangeByCountry": {
      "GB": -4,
      "US": -1,
      "DE": -1,
      "FR": 1,
      "ES": 0,
      "AT": 0,
      "SE": 0,
      "IT": 0,
      "CN": 0,
      "NL": -1,
      "AU": 0,
      "PL": -1,
      "NZ": 0,
      "RU": 0,
      "ID": 0,
      "BD": 0,
      "FI": 0,
      "CA": 0,
      "MX": 1,
      "RO": 0,
      "IE": 0,
      "TR": 0,
      "BR": 0,
      "CH": 0,
      "VN": 0,
      "DZ": 0,
      "TT": 0,
      "TW": 0,
      "BE": 0,
      "NO": 0,
      "KE": 0,
      "PK": 0,
      "IN": 0,
      "DK": 0,
      "SO": 0,
      "PH": 0,
      "EG": 0,
      "TH": 0,
      "JP": 0
    }
  },
  "managedInfo": {
    "totalNonStaleRecentDevices": 564,
    "totalRecent24hDevices": 86,
    "totalLicensedDevices": 0,
    "devicesByOS": {
      "25": 9,
      "28": 3,
      "29": 1,
      "30": 149,
      "31": 5,
      "32": 8,
      "33": 8,
      "34": 18,
      "35": 292,
      "36": 71
    },
    "devicesByMake": {
      "motorola": 191,
      "OnePlus": 137,
      "Google": 78,
      "samsung": 35,
      "Crosscall": 28,
      "HMD Global": 19,
      "TCL": 16,
      "Fairphone": 13,
      "Unihertz": 10,
      "NUU": 8,
      "OUKITEL": 7,
      "Elo Touch Solutions": 4,
      "LENOVO": 3,
      "HUAWEI": 2,
      "Blackview": 2,
      "Xiaomi": 2,
      "OPPO": 2,
      "unknown": 2,
      "INFINIX": 1,
      "TDTECH": 1,
      "Honeywell": 1,
      "Zebra Technologies": 1,
      "SMT_HK": 1
    },
    "devicesByCountry": {
      "AU": 180,
      "GB": 165,
      "US": 149,
      "BE": 13,
      "ZA": 6,
      "DE": 6,
      "IT": 5,
      "NG": 3,
      "SG": 3,
      "PH": 3,
      "NZ": 3,
      "CA": 3,
      "FI": 2,
      "JM": 2,
      "ID": 2,
      "IE": 2,
      "TT": 2,
      "IN": 2,
      "CN": 2,
      "ET": 1,
      "RO": 1,
      "BR": 1,
      "TR": 1,
      "BD": 1,
      "NL": 1,
      "MX": 1,
      "FR": 1,
      "TW": 1,
      "YE": 1,
      "PL": 1
    },
    "numberChangeByOS": {
      "25": 0,
      "28": 0,
      "29": 0,
      "30": 2,
      "31": 0,
      "32": 1,
      "33": 0,
      "34": 0,
      "35": 9,
      "36": -7
    },
    "numberChangeByMake": {
      "motorola": 6,
      "OnePlus": 2,
      "Google": -7,
      "samsung": 4,
      "Crosscall": 0,
      "HMD Global": 0,
      "TCL": 0,
      "Fairphone": 0,
      "Unihertz": 0,
      "NUU": 0,
      "OUKITEL": -1,
      "Elo Touch Solutions": 0,
      "LENOVO": 0,
      "HUAWEI": 0,
      "Blackview": 0,
      "Xiaomi": 0,
      "OPPO": 0,
      "unknown": 0,
      "INFINIX": 0,
      "TDTECH": 0,
      "Honeywell": 0,
      "Zebra Technologies": 0,
      "SMT_HK": 1
    },
    "numberChangeByCountry": {
      "AU": 6,
      "GB": -6,
      "US": 2,
      "BE": -1,
      "ZA": 0,
      "DE": 0,
      "IT": 5,
      "NG": 0,
      "SG": 0,
      "PH": 0,
      "NZ": 0,
      "CA": 0,
      "FI": 0,
      "JM": 0,
      "ID": 0,
      "IE": 0,
      "TT": 0,
      "IN": 0,
      "CN": -1,
      "ET": 0,
      "RO": 0,
      "BR": 0,
      "TR": 0,
      "BD": 0,
      "NL": 0,
      "MX": 0,
      "FR": 0,
      "TW": 0,
      "YE": 0,
      "PL": 0
    }
  }
}